secret_token.py
secret_token-1.0.2.dist-info/LICENSE
secret_token-1.0.2.dist-info/METADATA
secret_token-1.0.2.dist-info/WHEEL
secret_token-1.0.2.dist-info/top_level.txt
secret_token-1.0.2.dist-info/RECORD
