Metadata-Version: 2.1
Name: secret-token
Version: 1.0.2
Summary: Easy manipulation of RFC8959 secret-token URIs
Home-page: https://github.com/Lexicality/secret-token
Author: Lex Robinson
Author-email: lexi@lexi.org.uk
License: Apache-2.0
Keywords: rfc8959
Platform: UNKNOWN
Classifier: Development Status :: 5 - Production/Stable
Classifier: License :: OSI Approved :: Apache Software License
Classifier: Programming Language :: Python :: 3.6
Classifier: Programming Language :: Python :: 3.7
Classifier: Programming Language :: Python :: 3.8
Classifier: Programming Language :: Python :: 3.9
Classifier: Topic :: Security
Classifier: Topic :: Utilities
Requires-Python: ~=3.6
